Funnel Shifter/shifter.v
module fb(i, o, kind_shift, s_count);
    input [7:0] i;
    output reg [7:0] o;
    reg [15:0] temp;
    reg [7:0] c;
    reg [7:0] s;
    input [2:0] kind_shift;
    input [3:0] s_count;

always @(i or kind_shift or s or s_count) begin
    case(kind_shift)
        3'b000: begin
            c = i[7:0];
            s = 8'b0;
            temp = {s, c};
            case(s_count)
		        4'b0000: temp = temp;
		        4'b0001: temp = {temp[14:0], temp[15]};
		        4'b0010: temp = {temp[13:0], temp[15:14]};
		        4'b0011: temp = {temp[12:0], temp[15:13]};
		        4'b0100: temp = {temp[11:0], temp[15:12]};
		        4'b0101: temp = {temp[10:0], temp[15:11]};
		        4'b0110: temp = {temp[9:0], temp[15:10]};
		        4'b0111: temp = {temp[8:0], temp[15:9]};
                default: temp = temp;
	        endcase
            o = temp[7:0];
        end
        3'b001: begin
            c = 8'b0;
            s = i[7:0];
            temp = {s, c};
            case(4'b1000-s_count)
		        4'b0000: temp = temp;
		        4'b0001: temp = {temp[14:0], temp[15]};
		        4'b0010: temp = {temp[13:0], temp[15:14]};
		        4'b0011: temp = {temp[12:0], temp[15:13]};
		        4'b0100: temp = {temp[11:0], temp[15:12]};
		        4'b0101: temp = {temp[10:0], temp[15:11]};
		        4'b0110: temp = {temp[9:0], temp[15:10]};
		        4'b0111: temp = {temp[8:0], temp[15:9]};
                default: temp = temp;
	        endcase
            o = temp[7:0];
        end
        3'b010: begin
            c = i[7:0];
            s = {8{i[7]}};
            temp = {s, c};
            case(s_count)
		        4'b0000: temp = temp;
		        4'b0001: temp = {temp[14:0], temp[15]};
		        4'b0010: temp = {temp[13:0], temp[15:14]};
		        4'b0011: temp = {temp[12:0], temp[15:13]};
		        4'b0100: temp = {temp[11:0], temp[15:12]};
		        4'b0101: temp = {temp[10:0], temp[15:11]};
		        4'b0110: temp = {temp[9:0], temp[15:10]};
		        4'b0111: temp = {temp[8:0], temp[15:9]};
                default: temp = temp;
	        endcase
            o = temp[7:0];
        end
        3'b011: begin
            c = 8'b0;
            s = i[7:0];
            temp = {s, c};
            case(4'b1000-s_count)
		        4'b0000: temp = temp;
		        4'b0001: temp = {temp[14:0], temp[15]};
		        4'b0010: temp = {temp[13:0], temp[15:14]};
		        4'b0011: temp = {temp[12:0], temp[15:13]};
		        4'b0100: temp = {temp[11:0], temp[15:12]};
		        4'b0101: temp = {temp[10:0], temp[15:11]};
		        4'b0110: temp = {temp[9:0], temp[15:10]};
		        4'b0111: temp = {temp[8:0], temp[15:9]};
                default: temp = temp;
	        endcase
            o = temp[7:0];
        end
        3'b100: begin
            c = i[7:0];
            s = i[7:0];
            temp = {s, c};
            case(s_count)
		        4'b0000: temp = temp;
		        4'b0001: temp = {temp[14:0], temp[15]};
		        4'b0010: temp = {temp[13:0], temp[15:14]};
		        4'b0011: temp = {temp[12:0], temp[15:13]};
		        4'b0100: temp = {temp[11:0], temp[15:12]};
		        4'b0101: temp = {temp[10:0], temp[15:11]};
		        4'b0110: temp = {temp[9:0], temp[15:10]};
		        4'b0111: temp = {temp[8:0], temp[15:9]};
                default: temp = temp;
	        endcase
            o = temp[7:0];
        end
        3'b101: begin
            c = i[7:0];
            s = i[7:0];
            temp = {s, c};
            case(4'b1000-s_count)
		        4'b0000: temp = temp;
		        4'b0001: temp = {temp[14:0], temp[15]};
		        4'b0010: temp = {temp[13:0], temp[15:14]};
		        4'b0011: temp = {temp[12:0], temp[15:13]};
		        4'b0100: temp = {temp[11:0], temp[15:12]};
		        4'b0101: temp = {temp[10:0], temp[15:11]};
		        4'b0110: temp = {temp[9:0], temp[15:10]};
		        4'b0111: temp = {temp[8:0], temp[15:9]};
                default: temp = temp;
	        endcase
            o = temp[7:0];
        end
        default: o = c;
    endcase
end
endmodule

Funnel Shifter/test.v
module top;
reg	[7:0]	i;
reg [2:0] kind_shift;
reg [3:0] s_count;
wire [7:0]	o;

fb dut(i, o, kind_shift, s_count);

//------여기서 부터 아래 선까지는 waveform을 보기위한 파일을 만드는 코드이다.---- 
initial begin
      $dumpfile("test_out.vcd");
      $dumpvars(-1,dut);  // tb는 위에 nand4_if tb(a,y)의 tb를 말한다. 
      $monitor("%b",o);
end
//------------------------------------------------------------------------------

initial begin
	i = 8'b00000010;
    kind_shift = 3'b000;
    s_count = 4'b0001;
	#100;
	i = 8'b00000010;
    kind_shift = 3'b001;
    s_count = 4'b0001;
	#100;

	i = 8'b00000010;
    kind_shift = 3'b010;
    s_count = 4'b0001;
	#100;
	i = 8'b00000010;
    kind_shift = 3'b011;
    s_count = 4'b0001;
	#100;
	i = 8'b00000010;
    kind_shift = 3'b100;
    s_count = 4'b0001;
	#100;
	i = 8'b00000010;
    kind_shift = 3'b101;
    s_count = 4'b0001;
	#100;

    
    i = 8'b11111110;
    kind_shift = 3'b000;
    s_count = 1'b1;
	#100;
	i = 8'b11111110;
    kind_shift = 3'b001;
    s_count = 1'b1;
	#100;
	i = 8'b11111110;
    kind_shift = 3'b010;
    s_count = 1'b1;
	#100;
	i = 8'b11111110;
    kind_shift = 3'b011;
    s_count = 1'b1;
	#100;
	i = 8'b11111110;
    kind_shift = 3'b100;
    s_count = 1'b1;
	#100;
	i = 8'b11111110;
    kind_shift = 3'b101;
    s_count = 1'b1;
	#100;
    
end
endmodule

Funnel Shifter/test_out.vcd
$date
	Fri Mar 05 19:06:39 2021
$end
$version
	Icarus Verilog
$end
$timescale
	1s
$end
$scope module top $end
$scope module dut $end
$var wire 8 ! i [7:0] $end
$var wire 3 " kind_shift [2:0] $end
$var wire 4 # s_count [3:0] $end
$var reg 8 $ c [7:0] $end
$var reg 8 % o [7:0] $end
$var reg 8 & s [7:0] $end
$var reg 16 ' temp [15:0] $end
$upscope $end
$upscope $end
$enddefinitions $end
#0
$dumpvars
b100 '
b0 &
b100 %
b10 $
b1 #
b0 "
b10 !
$end
#100
b1 %
b1 '
b10 &
b0 $
b1 "
#200
b100 %
b100 '
b0 &
b10 $
b10 "
#300
b1 %
b1 '
b10 &
b0 $
b11 "
#400
b100 %
b10000000100 '
b10 $
b100 "
#500
b1 %
b100000001 '
b101 "
#600
b11111100 %
b111111100 '
b0 &
b11111110 $
b0 "
b11111110 !
#700
b1111111 %
b1111111 '
b11111110 &
b0 $
b1 "
#800
b11111101 %
b1111111111111101 '
b11111111 &
b11111110 $
b10 "
#900
b1111111 %
b1111111 '
b11111110 &
b0 $
b11 "
#1000
b11111101 %
b1111110111111101 '
b11111110 $
b100 "
#1100
b1111111 %
b111111101111111 '
b101 "
